Houston/__init__.py
Houston/admin.py
Houston/forms.py
Houston/middleware.py
Houston/models.py
Houston/settings.py
Houston/urls.py
Houston/utils.py
Houston/views.py
Houston/management/__init__.py
Houston/management/commands/__init__.py
Houston/management/commands/fub_views.py
Houston/migrations/0001_initial.py
Houston/migrations/0002_auto_20170305_0028.py
Houston/migrations/0003_auto_20170307_0045.py
Houston/migrations/__init__.py
Houston/static/Houston/.gitignore
Houston/static/Houston/js/ajax.js
Houston/static/Houston/js/d3.js
Houston/static/Houston/js/dashboard.js
Houston/static/Houston/js/jquery.js
Houston/static/Houston/js/line-chart.js
Houston/static/Houston/js/require.js
Houston/static/Houston/js/tracker.js
Houston/static/Houston/js/views-chart.js
Houston/static/js/tracker.js
Houston/templates/Houston/base.html
Houston/templates/Houston/dashboard.html
Houston/templates/Houston/require.html
Houston/templates/Houston/tracking.html
testsite/migrations/__init__.py
django_houston-0.3.0.dist-info/LICENSE
django_houston-0.3.0.dist-info/METADATA
django_houston-0.3.0.dist-info/WHEEL
django_houston-0.3.0.dist-info/top_level.txt
django_houston-0.3.0.dist-info/RECORD
