Metadata-Version: 2.1
Name: django-houston
Version: 0.3.0
Summary: Straightforward analytics that don't involve shipping your data to "Someone Else"
Home-page: https://github.com/RyanJenkins/Houston
Author: Lanny
Author-email: lan.rogers.book@gmail.com
License: GPL v3.0
Platform: UNKNOWN
Classifier: Environment :: Web Environment
Classifier: Framework :: Django
Classifier: Framework :: Django :: 1.10
Classifier: Intended Audience :: Developers
Classifier: License :: OSI Approved :: GNU General Public License v3 (GPLv3)
Classifier: Operating System :: OS Independent
Classifier: Programming Language :: Python
Classifier: Programming Language :: Python :: 2
Classifier: Programming Language :: Python :: 2.7
Classifier: Topic :: Internet :: WWW/HTTP
Classifier: Topic :: Internet :: WWW/HTTP :: Dynamic Content
